LICENSE
MANIFEST.in
README.md
requirements.txt
setup.py
quantiphyse_fsl/__init__.py
quantiphyse_fsl/_version.py
quantiphyse_fsl/flirt.py
quantiphyse_fsl/flirt_transform.py
quantiphyse_fsl/fnirt.py
quantiphyse_fsl/fsl.png
quantiphyse_fsl/fsl.svg
quantiphyse_fsl/process.py
quantiphyse_fsl/tests.py
quantiphyse_fsl/widget.py
quantiphyse_fsl.egg-info/PKG-INFO
quantiphyse_fsl.egg-info/SOURCES.txt
quantiphyse_fsl.egg-info/dependency_links.txt
quantiphyse_fsl.egg-info/entry_points.txt
quantiphyse_fsl.egg-info/requires.txt
quantiphyse_fsl.egg-info/top_level.txt